freegrad/__init__.py
freegrad/context.py
freegrad/functional.py
freegrad/hook.py
freegrad/registry.py
freegrad/wrappers.py
freegrad/transforms/__init__.py
freegrad/transforms/basic.py
freegrad/transforms/jamming.py
freegrad-1.0.0.dist-info/licenses/LICENSE
freegrad-1.0.0.dist-info/METADATA
freegrad-1.0.0.dist-info/WHEEL
freegrad-1.0.0.dist-info/top_level.txt
freegrad-1.0.0.dist-info/RECORD
