Metadata-Version: 2.4
Name: freegrad
Version: 1.0.0
Summary: A PyTorch extension for experimenting with alternative gradient flows.
Author-email: Luigi Troiano <ltroiano@unisa.it>, Gioele Ciaparrone <gioele.ciaparrone@kebula.it>, Genny Tortora <gtortora@unisa.it>
License: MIT License
Keywords: pytorch,autograd,gradients
Classifier: Programming Language :: Python :: 3
Classifier: License :: OSI Approved :: MIT License
Classifier: Operating System :: OS Independent
Classifier: Topic :: Scientific/Engineering :: Artificial Intelligence
Requires-Python: >=3.9
License-File: LICENSE
Requires-Dist: torch>=2.0.0
Requires-Dist: torchvision>=0.15
Provides-Extra: dev
Requires-Dist: pytest>=7.0; extra == "dev"
Requires-Dist: pytest-cov>=4.0; extra == "dev"
Requires-Dist: ruff>=0.4; extra == "dev"
Requires-Dist: black>=24.0; extra == "dev"
Requires-Dist: mypy>=1.8; extra == "dev"
Requires-Dist: build>=1.2.1; extra == "dev"
Requires-Dist: twine>=5.0.0; extra == "dev"
Requires-Dist: numpy>=1.24; extra == "dev"
Requires-Dist: scipy>=1.10; extra == "dev"
Requires-Dist: scikit-learn>=1.2.0; extra == "dev"
Requires-Dist: pre-commit>=4.3.0; extra == "dev"
Requires-Dist: pandoc>=2.4; extra == "dev"
Dynamic: license-file
